qs_params-0.2.5.dist-info/DESCRIPTION.rst
qs_params-0.2.5.dist-info/LICENSE.txt
qs_params-0.2.5.dist-info/METADATA
qs_params-0.2.5.dist-info/RECORD
qs_params-0.2.5.dist-info/WHEEL
qs_params-0.2.5.dist-info/metadata.json
qs_params-0.2.5.dist-info/top_level.txt
tests/__init__.py
tests/basic-test.py
tests/brackets-to-dots-test.py
tests/deserialize-test.py
tests/keys-to-brackets-test.py
tests/serialize-test.py
