Metadata-Version: 2.0
Name: qs-params
Version: 0.2.5
Summary: query string serializer/deserializer
Home-page: https://github.com/pyKilt/qs_params
Author: Jesus Germade
Author-email: jesus@germade.es
License: MIT
Keywords: querystring,query,string,serializer,deserializer,serialize,deserialize
Platform: UNKNOWN
